Compiled from "Test2.java"
public class Test2 {
  public Test2();
    Code:
       0: aload_0
       1: invokespecial #1                  // Method java/lang/Object."<init>":()V
       4: return

  public static int sum_for(int);
    Code:
       0: iconst_0
       1: istore_1
       2: iconst_0
       3: istore_2
       4: iconst_0
       5: istore_1
       6: iload_1
       7: iload_0
       8: if_icmpgt     21
      11: iload_2
      12: iload_1
      13: iadd
      14: istore_2
      15: iinc          1, 1
      18: goto          6
      21: iload_2
      22: ireturn

  public static void main(java.lang.String[]);
    Code:
       0: getstatic     #7                  // Field java/lang/System.out:Ljava/io/PrintStream;
       3: iconst_3
       4: invokestatic  #13                 // Method sum_for:(I)I
       7: invokedynamic #19,  0             // InvokeDynamic #0:makeConcatWithConstants:(I)Ljava/lang/String;
      12: invokevirtual #23                 // Method java/io/PrintStream.println:(Ljava/lang/String;)V
      15: return
}
